LICENSE
MANIFEST.in
README.md
requirements.txt
setup.py
restli/__init__.py
restli/command_line.py
restli/generators.py
restli/scaffolders.py
restli/utils.py
restli.egg-info/PKG-INFO
restli.egg-info/SOURCES.txt
restli.egg-info/dependency_links.txt
restli.egg-info/entry_points.txt
restli.egg-info/requires.txt
restli.egg-info/top_level.txt
restli/templates/DataTemplate.pdsc
restli/templates/Resource.java
restli/templates/TestResource.java
restli/templates/__init__.py
restli/templates/api_build.gradle
restli/templates/server_build.gradle
restli/templates/server_settings.gradle
restli/templates/toplevel_build.gradle
restli/templates/toplevel_settings.gradle