Metadata-Version: 1.1
Name: restli
Version: 0.2
Summary: Command line tools for scaffolding a Rest.li project
Home-page: https://github.com/cbrentharris/restli-cli
Author: Christopher Harris
Author-email: cbrentharris@gmail.com
License: UNKNOWN
Download-URL: https://github.com/cbrentharris/restli-cli/archive/master.zip
Platform: UNKNOWN
